feedbackqa_bart/__init__.py
feedbackqa_bart-0.1.0rc2.dist-info/METADATA
feedbackqa_bart-0.1.0rc2.dist-info/WHEEL
feedbackqa_bart-0.1.0rc2.dist-info/top_level.txt
feedbackqa_bart-0.1.0rc2.dist-info/RECORD
