Metadata-Version: 2.1
Name: feedbackqa-bart
Version: 0.1.0rc2
Summary: BART Model for FQA
Home-page: UNKNOWN
Author: Xing Han Lu
Author-email: github@xinghanlu.com
License: UNKNOWN
Platform: UNKNOWN
Classifier: Programming Language :: Python :: 3.6
Classifier: Programming Language :: Python :: 3.7
Classifier: Programming Language :: Python :: 3.8
Classifier: Programming Language :: Python :: 3.9
Classifier: License :: OSI Approved :: MIT License
Classifier: Operating System :: OS Independent
Requires-Python: >=3.6
Requires-Dist: torchtext (==0.6.0)
Requires-Dist: parlai
Requires-Dist: bert-reranker
Requires-Dist: transformers
Requires-Dist: torch
Requires-Dist: numpy
Requires-Dist: tqdm
